{
  "tracks": [
    {
      "mode": 0,
      "title": "ビバ!マッチョ / マッチョ29",
      "url": "https://yt.8uro.net/r?v=https://www.youtube.com/watch?v=26zZk_33Dek"
    },
    {
      "mode": 0,
      "title": "マッスルレボリューション（Muscle revolution） | NHK",
      "url": "https://yt.8uro.net/r?v=https://www.youtube.com/watch?v=E9CZkLCsh7Y"
    },
    {
      "mode": 0,
      "title": "JUST DO IT!",
      "url": "https://yt.8uro.net/r?v=https://www.youtube.com/watch?v=nwW4CDGucVs"
    },
    {
      "mode": 0,
      "title": "ビバ!マッチョ 振り付け練習動画 / マッチョ29 / ゆえちゃん",
      "url": "https://yt.8uro.net/r?v=https://www.youtube.com/watch?v=aEZmYSDL-Uw"
    },
    {
      "mode": 0,
      "title": "[みんなで筋肉体操] シーズン6 下半身サーキット(後半) | NHK",
      "url": "https://yt.8uro.net/r?v=https://www.youtube.com/watch?v=9uVaABCctOg"
    },
    {
      "mode": 0,
      "title": "YATTA / はっぱ隊",
      "url": "https://yt.8uro.net/r?v=https://www.youtube.com/watch?v=-pr-WUa8eEs"
    },
    {
      "mode": 0,
      "title": "[RIZAP]夜に駆ける / YOASOBI",
      "url": "https://yt.8uro.net/r?v=https://www.youtube.com/watch?v=e1VC2lgTWes"
    },
    {
      "mode": 0,
      "title": "[たかちゃんマンch] 紅蓮華 -LiSA",
      "url": "https://yt.8uro.net/r?v=https://www.youtube.com/watch?v=NjYV_DFzCLQ"
    },
    {
      "mode": 0,
      "title": "[みんなで筋肉体操] シーズン5 太ももと尻(2/2) | NHK",
      "url": "https://yt.8uro.net/r?v=https://www.youtube.com/watch?v=sSbWH4y5Ees"
    },
    {
      "mode": 0,
      "title": "[あんなさん]ロコローション - ORANGE RANGE",
      "url": "https://yt.8uro.net/r?v=https://www.youtube.com/watch?v=pKrAWDavwvs"
    },
    {
      "mode": 0,
      "title": "[みんなで筋肉体操] シーズン5 肩(2/2) | NHK",
      "url": "https://yt.8uro.net/r?v=https://www.youtube.com/watch?v=LG-zfh6JzV8"
    },
    {
      "mode": 0,
      "title": "[Hinoi Team]Night of fire - NIKO",
      "url": "https://yt.8uro.net/r?v=https://www.youtube.com/watch?v=aTBlKRzNf74"
    },
    {
      "mode": 0,
      "title": "[みんなで筋肉体操] シーズン5 太ももと尻（スクワット2種） | NHK",
      "url": "https://yt.8uro.net/r?v=https://www.youtube.com/watch?v=qgCIjWNjFLc"
    },
    {
      "mode": 0,
      "title": "[ジェットゆう]2002 / Anne-Marie",
      "url": "https://yt.8uro.net/r?v=https://www.youtube.com/watch?v=gDQDPTC-a-Y"
    },
    {
      "mode": 0,
      "title": "[後半用][MELOS]スクワット三種",
      "url": "https://yt.8uro.net/r?v=https://www.youtube.com/watch?v=o0VA-Du0CX0"
    },
    {
      "mode": 0,
      "title": "[前半用][りるちゃんねる]CAT'S EYE",
      "url": "https://yt.8uro.net/r?v=https://www.youtube.com/watch?v=2Q4dzdW0eGI"
    },
    {
      "mode": 0,
      "title": "[後半用][脂肪燃焼ちゃん]胴2分 曲目不明",
      "url": "https://yt.8uro.net/r?v=https://www.youtube.com/watch?v=q6jUYgSqqGg"
    },
    {
      "mode": 0,
      "title": "[前半用][Marshall]10:35 - @TateMcRae & @tiesto ",
      "url": "https://yt.8uro.net/r?v=https://www.youtube.com/watch?v=M0sS2tkoZTY"
    },
    {
      "mode": 0,
      "title": "[後半][CoCoDakara]スクワット",
      "url": "https://yt.8uro.net/r?v=https://www.youtube.com/watch?v=GrMnlD5DENg"
    },
    {
      "mode": 0,
      "title": "[後半][CoCoDakara]パルススクワット",
      "url": "https://yt.8uro.net/r?v=https://www.youtube.com/watch?v=uiEYsiewZ00"
    },
    {
      "mode": 0,
      "title": "[前半][Cardio(後ろ姿)]恋のマイアヒ・エアロビVer",
      "url": "https://yt.8uro.net/r?v=https://www.youtube.com/watch?v=c1hzbBFIno4"
    },
    {
      "mode": 0,
      "title": "[後半][Qool]立ち腹筋2分",
      "url": "https://yt.8uro.net/r?v=https://www.youtube.com/watch?v=JUSBE__5zag"
    },
    {
      "mode": 0,
      "title": "[後半][MELOS]ランジ3セット",
      "url": "https://yt.8uro.net/r?v=https://www.youtube.com/watch?v=ZRfEIEeWh0I"
    },
    {
      "mode": 0,
      "title": "[前半][たけまり]Turn Up The Love - Otto Wallgren feat. Stina Sundstrom",
      "url": "https://yt.8uro.net/r?v=https://www.youtube.com/watch?v=g_V2QxlC0SA"
    },
    {
      "mode": 0,
      "title": "[前半][STUDIO SUM]【UFO】ピンク・レディー",
      "url": "https://yt.8uro.net/r?v=https://www.youtube.com/watch?v=3iqmiYHK8vM"
    },
    {
      "mode": 0,
      "title": "[後半][MELOS]カーフレイズ30回3セット",
      "url": "https://yt.8uro.net/r?v=https://www.youtube.com/watch?v=oVbkeODJNSE"
    }
  ]
}